[
  {
    "fullName": "Emmitt Benally",
    "boughtCars": 5,
    "spentMoney": [
      5309.59,
      361.27,
      1322.64,
      256.89,
      259.97
    ]
  },
  {
    "fullName": "Natalie Poli",
    "boughtCars": 3,
    "spentMoney": [
      872.76,
      3013.10,
      1127.14
    ]
  },
  {
    "fullName": "Marcelle Griego",
    "boughtCars": 3,
    "spentMoney": [
      1741.55,
      231.97,
      4588.44
    ]
  },
  {
    "fullName": "Zada Attwood",
    "boughtCars": 4,
    "spentMoney": [
      4697.83,
      330.97,
      5722.10,
      472.97
    ]
  },
  {
    "fullName": "Hai Everton",
    "boughtCars": 2,
    "spentMoney": [
      412.20,
      5605.41
    ]
  },
  {
    "fullName": "Lino Subia",
    "boughtCars": 2,
    "spentMoney": [
      552.50,
      3696.41
    ]
  },
  {
    "fullName": "Rico Peer",
    "boughtCars": 2,
    "spentMoney": [
      2276.16,
      623.81
    ]
  },
  {
    "fullName": "Teddy Hobby",
    "boughtCars": 5,
    "spentMoney": [
      2602.32,
      590.15,
      111.38,
      3701.89,
      2792.12
    ]
  },
  {
    "fullName": "Johnette Derryberry",
    "boughtCars": 3,
    "spentMoney": [
      3258.65,
      1061.29,
      1166.92
    ]
  },
  {
    "fullName": "Audrea Cardinal",
    "boughtCars": 3,
    "spentMoney": [
      4593.75,
      2448.92,
      1671.59
    ]
  },
  {
    "fullName": "Francis Mckim",
    "boughtCars": 2,
    "spentMoney": [
      276.92,
      344.22
    ]
  },
  {
    "fullName": "Carole Witman",
    "boughtCars": 2,
    "spentMoney": [
      3696.41,
      281.17
    ]
  },
  {
    "fullName": "Oren Perlman",
    "boughtCars": 4,
    "spentMoney": [
      1424.94,
      1932.56,
      3238.88,
      2537.89
    ]
  },
  {
    "fullName": "Brett Brickley",
    "boughtCars": 2,
    "spentMoney": [
      1968.86,
      1397.15
    ]
  },
  {
    "fullName": "Kristian Engberg",
    "boughtCars": 3,
    "spentMoney": [
      1227.97,
      2253.29,
      332.96
    ]
  },
  {
    "fullName": "Carri Knapik",
    "boughtCars": 4,
    "spentMoney": [
      6180.59,
      4166.92,
      556.97,
      646.15
    ]
  },
  {
    "fullName": "Rema Revelle",
    "boughtCars": 1,
    "spentMoney": [
      2341.64
    ]
  },
  {
    "fullName": "Taina Achenbach",
    "boughtCars": 2,
    "spentMoney": [
      1309.85,
      298.97
    ]
  },
  {
    "fullName": "Yvonne Mccalla",
    "boughtCars": 1,
    "spentMoney": [
      1003.78
    ]
  },
  {
    "fullName": "Nisha Markwell",
    "boughtCars": 1,
    "spentMoney": [
      5347.84
    ]
  },
  {
    "fullName": "Cinthia Lasala",
    "boughtCars": 5,
    "spentMoney": [
      208.92,
      3931.19,
      906.27,
      931.20,
      3340.10
    ]
  },
  {
    "fullName": "Daniele Zarate",
    "boughtCars": 3,
    "spentMoney": [
      555.96,
      2161.32,
      228.90
    ]
  },
  {
    "fullName": "Faustina Burgher",
    "boughtCars": 4,
    "spentMoney": [
      2547.57,
      1111.96,
      5469.53,
      3456.83
    ]
  },
  {
    "fullName": "Jimmy Grossi",
    "boughtCars": 3,
    "spentMoney": [
      4992.94,
      2353.94,
      3035.24
    ]
  },
  {
    "fullName": "Sylvie Mcelravy",
    "boughtCars": 2,
    "spentMoney": [
      198.42,
      382.97
    ]
  },
  {
    "fullName": "Hipolito Lamoreaux",
    "boughtCars": 6,
    "spentMoney": [
      660.91,
      615.23,
      275.97,
      169.90,
      1142.96,
      1674.11
    ]
  },
  {
    "fullName": "Garret Capron",
    "boughtCars": 3,
    "spentMoney": [
      3327.10,
      4648.46,
      3768.03
    ]
  },
  {
    "fullName": "Donnetta Soliz",
    "boughtCars": 3,
    "spentMoney": [
      274.85,
      2410.05,
      344.88
    ]
  },
  {
    "fullName": "Louann Holzworth",
    "boughtCars": 3,
    "spentMoney": [
      88.88,
      3112.31,
      1999.84
    ]
  },
  {
    "fullName": "Ann Mcenaney",
    "boughtCars": 2,
    "spentMoney": [
      195.97,
      325.88
    ]
  }
]